langchain_unstructured/__init__.py
langchain_unstructured/document_loaders.py
langchain_unstructured/py.typed
gigachain_unstructured-0.1.2.dist-info/LICENSE
gigachain_unstructured-0.1.2.dist-info/METADATA
gigachain_unstructured-0.1.2.dist-info/WHEEL
gigachain_unstructured-0.1.2.dist-info/RECORD
