Metadata-Version: 2.1
Name: gigachain-unstructured
Version: 0.1.2
Summary: An integration package connecting Unstructured and LangChain
Home-page: https://github.com/ai-forever/gigachain
License: MIT
Requires-Python: >=3.9,<4.0
Classifier: License :: OSI Approved :: MIT License
Classifier: Programming Language :: Python :: 3
Classifier: Programming Language :: Python :: 3.9
Classifier: Programming Language :: Python :: 3.10
Classifier: Programming Language :: Python :: 3.11
Classifier: Programming Language :: Python :: 3.12
Provides-Extra: local
Requires-Dist: gigachain-core (>=0.2.23,<0.3.0)
Requires-Dist: unstructured-client (>=0.25.0,<0.26.0)
Requires-Dist: unstructured[all-docs] (>=0.15.7,<0.16.0) ; (python_version < "3.13") and (extra == "local")
Project-URL: Repository, https://github.com/ai-forever/gigachain
Project-URL: Release Notes, https://github.com/ai-forever/gigachain/releases?q=tag%3A%22gigachain-unstructured%3D%3D0%22&expanded=true
Project-URL: Source Code, https://github.com/ai-forever/gigachain/tree/master/libs/partners/unstructured
